ansible_content_parser/__init__.py
ansible_content_parser/__main__.py
ansible_content_parser/_version.py
ansible_content_parser/gen_ftdata.py
ansible_content_parser/lint.py
ansible_content_parser/lintable_dict.py
ansible_content_parser/pipeline.py
ansible_content_parser/report.py
ansible_content_parser/safe_checks.py
ansible_content_parser/version.py
ansible_content_parser-1.0.7.dist-info/LICENSE
ansible_content_parser-1.0.7.dist-info/METADATA
ansible_content_parser-1.0.7.dist-info/WHEEL
ansible_content_parser-1.0.7.dist-info/entry_points.txt
ansible_content_parser-1.0.7.dist-info/top_level.txt
ansible_content_parser-1.0.7.dist-info/RECORD
