Metadata-Version: 2.2
Name: ansible-content-parser
Version: 1.0.7
Summary: The ansible content parser
Author-email: Tami Takamiya <ttakamiy@redhat.com>
Maintainer-email: Tami Takamiya <ttakamiy@redhat.com>
License: Apache
Project-URL: changelog, https://github.com/ansible/ansible-content-parser/releases
Project-URL: homepage, https://github.com/ansible/ansible-content-parser/
Project-URL: repository, https://github.com/ansible/ansible-content-parser/
Keywords: ansible
Classifier: Development Status :: 2 - Pre-Alpha
Classifier: Intended Audience :: Developers
Classifier: License :: OSI Approved :: Apache Software License
Classifier: Operating System :: OS Independent
Classifier: Programming Language :: Python :: 3 :: Only
Classifier: Programming Language :: Python :: 3
Classifier: Programming Language :: Python :: 3.10
Classifier: Programming Language :: Python :: 3.11
Classifier: Programming Language :: Python :: Implementation :: CPython
Classifier: Programming Language :: Python
Classifier: Topic :: Software Development
Classifier: Topic :: Utilities
Requires-Python: >=3.10
License-File: LICENSE
Requires-Dist: will-not-work-on-windows-try-from-wsl-instead; platform_system == "Windows"
Requires-Dist: ansible-lint==24.10.0
Requires-Dist: ansible-compat==24.10.0
Requires-Dist: GitPython
Requires-Dist: giturlparse
Requires-Dist: sarif-tools
Requires-Dist: sage-scan>=0.0.4
Requires-Dist: ansible-risk-insight>=0.2.9
Requires-Dist: black==24.4.2
Requires-Dist: pygit2
Provides-Extra: dev
Requires-Dist: black; extra == "dev"
Requires-Dist: mypy; extra == "dev"
Requires-Dist: pip-tools; extra == "dev"
Requires-Dist: pre-commit; extra == "dev"
Requires-Dist: pydoclint; extra == "dev"
Requires-Dist: pytest; extra == "dev"
Requires-Dist: ruff; extra == "dev"
Requires-Dist: toml-sort; extra == "dev"
Provides-Extra: lock
Provides-Extra: test
Requires-Dist: coverage[toml]>=6.4.4; extra == "test"
Requires-Dist: mypy; extra == "test"
Requires-Dist: pytest>=7.2.2; extra == "test"
Requires-Dist: tox==4.24.1; extra == "test"
Requires-Dist: build==1.2.2.post1; extra == "test"
